network_dismantling/__init__.py
network_dismantling/dismanlter/__init__.py
network_dismantling/dismanlter/basic/__init__.py
network_dismantling/dismanlter/basic/brute_force.py
network_dismantling/dismanlter/centrality/__init__.py
network_dismantling/dismanlter/centrality/betweenness.py
network_dismantling/dismanlter/centrality/degree.py
network_dismantling/dismanlter/dismantler.py
network_dismantling/dismanlter/influence/__init__.py
network_dismantling/dismanlter/influence/collective_influence.py
network_dismantling/dismanlter/influence/explosive_immunization.py
network_dismantling/dismanlter/optimization/__init__.py
network_dismantling/dismanlter/optimization/core_gdm.py
network_dismantling/dismanlter/optimization/core_hd.py
network_dismantling/dismanlter/optimization/gdm.py
network_dismantling/dismanlter/optimization/gnd.py
network_dismantling/evaluator/__init__.py
network_dismantling/evaluator/avg_clustering.py
network_dismantling/evaluator/avg_path_length.py
network_dismantling/evaluator/evaluator.py
network_dismantling/evaluator/global_effiency.py
network_dismantling/evaluator/lcc_size.py
network_dismantling/evaluator/num_components.py
network_dismantling-0.0.1.dist-info/METADATA
network_dismantling-0.0.1.dist-info/WHEEL
network_dismantling-0.0.1.dist-info/RECORD
