Metadata-Version: 2.1
Name: network-dismantling
Version: 0.0.1
Summary: Network Dismanling is a Network Dismantling Task Aimedextension library
License: MIT
Author: Command
Author-email: me@c0mm4nd.com
Requires-Python: >=3.8,<4.0
Classifier: License :: OSI Approved :: MIT License
Classifier: Programming Language :: Python :: 3
Classifier: Programming Language :: Python :: 3.8
Classifier: Programming Language :: Python :: 3.9
Classifier: Programming Language :: Python :: 3.10
Classifier: Programming Language :: Python :: 3.11
Classifier: Programming Language :: Python :: 3.12
Requires-Dist: networkx (>=3.3,<4.0)
